.gitignore
LICENSE
MANIFEST.in
Pipfile
Pipfile.lock
README.rst
setup.py
example/Makefile
example/make.bat
example/source/conf.py
example/source/example.rst
example/source/index.rst
example/source/test.py
src/sphinxcontrib/__init__.py
src/sphinxcontrib/gitinclude/__init__.py
src/sphinxcontrib_gitinclude.egg-info/PKG-INFO
src/sphinxcontrib_gitinclude.egg-info/SOURCES.txt
src/sphinxcontrib_gitinclude.egg-info/dependency_links.txt
src/sphinxcontrib_gitinclude.egg-info/namespace_packages.txt
src/sphinxcontrib_gitinclude.egg-info/not-zip-safe
src/sphinxcontrib_gitinclude.egg-info/requires.txt
src/sphinxcontrib_gitinclude.egg-info/top_level.txt