Metadata-Version: 2.1
Name: sphinxcontrib-gitinclude
Version: 0.0.1
Summary: Sphinx extension to include code from git repository
Home-page: https://sphinxcontrib-gitinclude.readthedocs.org/
Author: Oz Tiram
Author-email: oz.tiram@gmail.com
License: BSD
Keywords: sphinx git documentation
Platform: any
Classifier: Development Status :: 5 - Production/Stable
Classifier: Intended Audience :: Developers
Classifier: License :: OSI Approved :: BSD License
Classifier: Operating System :: OS Independent
Classifier: Programming Language :: Python :: 3.7
Classifier: Programming Language :: Python :: 3.8
Classifier: Programming Language :: Python :: 3.9
Classifier: Programming Language :: Python :: Implementation :: CPython
Classifier: Programming Language :: Python :: Implementation :: PyPy
Classifier: Topic :: Documentation
Classifier: Topic :: Utilities
Classifier: Framework :: Sphinx
Classifier: Framework :: Sphinx :: Extension
Requires-Python: >=3.7,!=3.0.*,!=3.1.*,!=3.2.*,!=3.3.*,!=3.4.*, !=3.5.*, !=3.6.*
License-File: LICENSE
